setup.cfg
setup.py
matialvarezs_django_celery_beat_handler/__init__.py
matialvarezs_django_celery_beat_handler/admin.py
matialvarezs_django_celery_beat_handler/apps.py
matialvarezs_django_celery_beat_handler/context_processors.py
matialvarezs_django_celery_beat_handler/decorators.py
matialvarezs_django_celery_beat_handler/definitions.py
matialvarezs_django_celery_beat_handler/dispatcher.py
matialvarezs_django_celery_beat_handler/errors.py
matialvarezs_django_celery_beat_handler/managers.py
matialvarezs_django_celery_beat_handler/middlewares.py
matialvarezs_django_celery_beat_handler/models.py
matialvarezs_django_celery_beat_handler/serializers.py
matialvarezs_django_celery_beat_handler/settings.py
matialvarezs_django_celery_beat_handler/signals.py
matialvarezs_django_celery_beat_handler/tests.py
matialvarezs_django_celery_beat_handler/urls.py
matialvarezs_django_celery_beat_handler/utils.py
matialvarezs_django_celery_beat_handler/views.py
matialvarezs_django_celery_beat_handler.egg-info/PKG-INFO
matialvarezs_django_celery_beat_handler.egg-info/SOURCES.txt
matialvarezs_django_celery_beat_handler.egg-info/dependency_links.txt
matialvarezs_django_celery_beat_handler.egg-info/requires.txt
matialvarezs_django_celery_beat_handler.egg-info/top_level.txt